{
	"format_version": "1.8.0",
	"animations": {
		"animation.weapon.hold_first_person": {
			"loop": true,
			"bones": {
				"root": {
					"rotation": [
						0,
						60,
						-130
					],
					"position": [
						5,
						35,
						0
					],
					"scale": [
						1.45,
						1.45,
						1.45
					]
				}
			}
		},
		"animation.weapon.hold_first_person_attack": {
			"loop": true,
			"animation_length": 1,
			"bones": {
				"root": {
					"rotation": {
						"0.0": [
							0,
							60,
							-130
						],
						"0.5": [
							90,
							60,
							-130
						],
						"1.0": [
							0,
							60,
							-130
						]
					},
					"position": [
						13,
						41,
						0
					],
					"scale": 2.15
				}
			}
		},
		"animation.weapon.hold_third_person": {
			"loop": true,
			"bones": {
				"root": {
					"rotation": [
						83,
						0,
						4
					],
					"position": [
						-0.8,
						23,
						8
					],
					"scale": [
						2.15,
						2.15,
						2.25
					]
				}
			}
		},
		"animation.weapon.hold_third_person2": {
			"loop": true,
			"bones": {
				"root": {
					"rotation": [
						83,
						0,
						4
					],
					"position": [
						-0.8,
						21.5,
						8
					],
					"scale": [
						2.15,
						2.15,
						2.25
					]
				}
			}
		},
		"animation.weapon.hold_third_person3": {
			"loop": true,
			"bones": {
				"root": {
					"rotation": [
						83,
						0,
						4
					],
					"position": [
						-0.8,
						19,
						8
					],
					"scale": [
						2.15,
						2.15,
						2.25
					]
				}
			}
		},
		"animation.weapon.chainsaw.hold_third_person": {
			"loop": true,
			"bones": {
				"root": {
					"rotation": [
						182.44971,
						-2.11885,
						-174.69678
					],
					"position": [
						-0.8,
						14,
						-5
					],
					"scale": [
						0.6,
						0.5,
						0.6
					]
				}
			}
		},
		"animation.weapon.chainsaw.hold_first_person": {
			"loop": true,
			"animation_length": 0.3,
			"bones": {
				"root": {
					"rotation": [
						-135.00253,
						-51.48405,
						62.5967
					],
					"position": [
						6,
						12,
						12
					]
				},
				"topSaws": {
					"position": {
						"0.0": [
							0,
							-14,
							0
						],
						"0.3": [
							0,
							-4,
							0
						]
					}
				},
				"downSaws": {
					"position": {
						"0.0": [
							0,
							0,
							0
						],
						"0.3": [
							0,
							-17,
							0
						]
					}
				}
			}
		}
	}
}